mypackage/__init__.py
mypackage/utils.py
mypackage_viraj-0.1.0.dist-info/METADATA
mypackage_viraj-0.1.0.dist-info/WHEEL
mypackage_viraj-0.1.0.dist-info/top_level.txt
mypackage_viraj-0.1.0.dist-info/RECORD
