Metadata-Version: 2.1
Name: mypackage-viraj
Version: 0.1.0
Summary: A demo package for greeting users
Home-page: 
Author: Your Name
Author-email: 
Classifier: Programming Language :: Python :: 3
Classifier: License :: OSI Approved :: MIT License
Classifier: Operating System :: OS Independent
Requires-Python: >=3.6
